itkwasm_transform_io_emscripten/__init__.py
itkwasm_transform_io_emscripten/_version.py
itkwasm_transform_io_emscripten/extension_to_transform_io.py
itkwasm_transform_io_emscripten/hdf5_read_transform_async.py
itkwasm_transform_io_emscripten/hdf5_write_transform_async.py
itkwasm_transform_io_emscripten/js_package.py
itkwasm_transform_io_emscripten/mat_read_transform_async.py
itkwasm_transform_io_emscripten/mat_write_transform_async.py
itkwasm_transform_io_emscripten/mnc_read_transform_async.py
itkwasm_transform_io_emscripten/mnc_write_transform_async.py
itkwasm_transform_io_emscripten/read_transform_async.py
itkwasm_transform_io_emscripten/transform_io_index.py
itkwasm_transform_io_emscripten/txt_read_transform_async.py
itkwasm_transform_io_emscripten/txt_write_transform_async.py
itkwasm_transform_io_emscripten/wasm_read_transform_async.py
itkwasm_transform_io_emscripten/wasm_write_transform_async.py
itkwasm_transform_io_emscripten/wasm_zstd_read_transform_async.py
itkwasm_transform_io_emscripten/wasm_zstd_write_transform_async.py
itkwasm_transform_io_emscripten/write_transform_async.py
itkwasm_transform_io_emscripten-1.1.0.dist-info/METADATA
itkwasm_transform_io_emscripten-1.1.0.dist-info/WHEEL
itkwasm_transform_io_emscripten-1.1.0.dist-info/RECORD
